MANIFEST.in
README.rst
setup.py
aliyun_python_sdk_aas.egg-info/PKG-INFO
aliyun_python_sdk_aas.egg-info/SOURCES.txt
aliyun_python_sdk_aas.egg-info/dependency_links.txt
aliyun_python_sdk_aas.egg-info/requires.txt
aliyun_python_sdk_aas.egg-info/top_level.txt
aliyunsdkaas/__init__.py
aliyunsdkaas/endpoint.py
aliyunsdkaas/request/__init__.py
aliyunsdkaas/request/v20150701/ChangePreferredLanguageRequest.py
aliyunsdkaas/request/v20150701/CheckMfaBindRequest.py
aliyunsdkaas/request/v20150701/CreateAccessKeyForAccountRequest.py
aliyunsdkaas/request/v20150701/CreateAliyunAccountRequest.py
aliyunsdkaas/request/v20150701/CreateAliyunAccountWithBindHidRequest.py
aliyunsdkaas/request/v20150701/CreateIntlAliyunAccountRequest.py
aliyunsdkaas/request/v20150701/CreateShortTermAccessKeyForAccountRequest.py
aliyunsdkaas/request/v20150701/DeleteAccessKeyForAccountRequest.py
aliyunsdkaas/request/v20150701/GenerateAccountLoginTokenRequest.py
aliyunsdkaas/request/v20150701/GetAliyunAccountWithBindHidRequest.py
aliyunsdkaas/request/v20150701/GetAliyunAccountWithBindTaobaoHidRequest.py
aliyunsdkaas/request/v20150701/GetBasicInfoForAccountRequest.py
aliyunsdkaas/request/v20150701/GetShortTermAccessKeyForAccountRequest.py
aliyunsdkaas/request/v20150701/ListAccessKeysForAccountRequest.py
aliyunsdkaas/request/v20150701/ListAliyunAccountRequest.py
aliyunsdkaas/request/v20150701/UpdateAccessKeyStatusForAccountRequest.py
aliyunsdkaas/request/v20150701/UpdatePasswordForAccountRequest.py
aliyunsdkaas/request/v20150701/UpdateStatusForAccountRequest.py
aliyunsdkaas/request/v20150701/VerifyAccountLoginTokenRequest.py
aliyunsdkaas/request/v20150701/__init__.py